{
    "assignmentCharacteristics": [
        {
            "command": "TB_OPTS=\"--count=0 --work_done_every_sec=0.5 --work_done_str=CPU0_work_done\" /root/thermobench/build/benchmarks/mem/membench -t1 -f -r -s 1000000",
            "resourceAssignments": [
                {
                    "intercept": 0.5341854404433324,
                    "length": 1000,
                    "processors": [
                        {
                            "processingUnits": 1,
                            "processor": "A53"
                        }
                    ],
                    "slope": 0.3539638540109318
                }
            ],
            "task": "0_membench-1M-RO-R"
        },
        {
            "command": "TB_OPTS=\"--count=0 --work_done_every_sec=0.5 --work_done_str=CPU1_work_done\" ./a2time-4K -v0 -c1 -i100",
            "resourceAssignments": [
                {
                    "intercept": 0.2044344560578661,
                    "length": 1000,
                    "processors": [
                        {
                            "processingUnits": 1,
                            "processor": "A53"
                        }
                    ],
                    "slope": 0.2418995207650015
                }
            ],
            "task": "1_a2time-4K"
        },
        {
            "command": "TB_OPTS=\"--count=0 --work_done_every_sec=0.5 --work_done_str=CPU2_work_done\" ./matrix-4M -v0 -c1 -i100",
            "resourceAssignments": [
                {
                    "intercept": 0.4230255145239212,
                    "length": 1000,
                    "processors": [
                        {
                            "processingUnits": 1,
                            "processor": "A53"
                        }
                    ],
                    "slope": 0.4313767949270035
                }
            ],
            "task": "2_matrix-4M"
        },
        {
            "command": "TB_OPTS=\"--count=0 --work_done_every_sec=0.5 --work_done_str=CPU3_work_done\" ./pntrch-4M -v0 -c1 -i1",
            "resourceAssignments": [
                {
                    "intercept": 0.274072044297375,
                    "length": 1000,
                    "processors": [
                        {
                            "processingUnits": 1,
                            "processor": "A53"
                        }
                    ],
                    "slope": 0.3437598877732618
                }
            ],
            "task": "3_pntrch-4M"
        },
        {
            "command": "TB_OPTS=\"--count=0 --work_done_every_sec=0.5 --work_done_str=CPU4_work_done\" /root/thermobench/build/benchmarks/mem/membench -t1 -f -s 1000000",
            "resourceAssignments": [
                {
                    "intercept": 0.9213932013879536,
                    "length": 1000,
                    "processors": [
                        {
                            "processingUnits": 1,
                            "processor": "A72"
                        }
                    ],
                    "slope": 0.8970942789843752
                }
            ],
            "task": "4_membench-1M-RO-S"
        },
        {
            "command": "TB_OPTS=\"--count=0 --work_done_every_sec=0.5 --work_done_str=CPU5_work_done\" ./canrdr-4K -v0 -c1 -i100",
            "resourceAssignments": [
                {
                    "intercept": 0.1047493941499277,
                    "length": 1000,
                    "processors": [
                        {
                            "processingUnits": 1,
                            "processor": "A72"
                        }
                    ],
                    "slope": 1.1068858215957862
                }
            ],
            "task": "5_canrdr-4K"
        }
    ],
    "environment": {
        "idlePower": 5.49,
        "majorFrameLength": 1000,
        "problemVersion": 1,
        "processors": [
            {
                "coreIds": [
                    0,
                    1,
                    2,
                    3
                ],
                "name": "A53",
                "processingUnits": 4,
                "type": "main_processor"
            },
            {
                "coreIds": [
                    4,
                    5
                ],
                "name": "A72",
                "processingUnits": 2,
                "type": "main_processor"
            }
        ],
        "scPart": 1.0
    },
    "solution": {
        "feasible": true,
        "solutionTime": 0,
        "solverMetadata": null,
        "solverName": "RandomGenerator",
        "windows": [
            {
                "length": 1000,
                "tasks": [
                    {
                        "length": 1000,
                        "processingUnit": 0,
                        "processor": "A53",
                        "start": 0,
                        "task": "0_membench-1M-RO-R"
                    },
                    {
                        "length": 1000,
                        "processingUnit": 1,
                        "processor": "A53",
                        "start": 0,
                        "task": "1_a2time-4K"
                    },
                    {
                        "length": 1000,
                        "processingUnit": 2,
                        "processor": "A53",
                        "start": 0,
                        "task": "2_matrix-4M"
                    },
                    {
                        "length": 1000,
                        "processingUnit": 3,
                        "processor": "A53",
                        "start": 0,
                        "task": "3_pntrch-4M"
                    },
                    {
                        "length": 1000,
                        "processingUnit": 0,
                        "processor": "A72",
                        "start": 0,
                        "task": "4_membench-1M-RO-S"
                    },
                    {
                        "length": 1000,
                        "processingUnit": 1,
                        "processor": "A72",
                        "start": 0,
                        "task": "5_canrdr-4K"
                    }
                ]
            }
        ]
    },
    "tasks": [
        {
            "assignmentIndex": 0,
            "command": "TB_OPTS=\"--count=0 --work_done_every_sec=0.5 --work_done_str=CPU0_work_done\" /root/thermobench/build/benchmarks/mem/membench -t1 -f -r -s 1000000",
            "length": 1000,
            "name": "0_membench-1M-RO-R",
            "processors": [
                {
                    "processingUnits": 1,
                    "processor": "A53"
                }
            ]
        },
        {
            "assignmentIndex": 0,
            "command": "TB_OPTS=\"--count=0 --work_done_every_sec=0.5 --work_done_str=CPU1_work_done\" ./a2time-4K -v0 -c1 -i100",
            "length": 1000,
            "name": "1_a2time-4K",
            "processors": [
                {
                    "processingUnits": 1,
                    "processor": "A53"
                }
            ]
        },
        {
            "assignmentIndex": 0,
            "command": "TB_OPTS=\"--count=0 --work_done_every_sec=0.5 --work_done_str=CPU2_work_done\" ./matrix-4M -v0 -c1 -i100",
            "length": 1000,
            "name": "2_matrix-4M",
            "processors": [
                {
                    "processingUnits": 1,
                    "processor": "A53"
                }
            ]
        },
        {
            "assignmentIndex": 0,
            "command": "TB_OPTS=\"--count=0 --work_done_every_sec=0.5 --work_done_str=CPU3_work_done\" ./pntrch-4M -v0 -c1 -i1",
            "length": 1000,
            "name": "3_pntrch-4M",
            "processors": [
                {
                    "processingUnits": 1,
                    "processor": "A53"
                }
            ]
        },
        {
            "assignmentIndex": 0,
            "command": "TB_OPTS=\"--count=0 --work_done_every_sec=0.5 --work_done_str=CPU4_work_done\" /root/thermobench/build/benchmarks/mem/membench -t1 -f -s 1000000",
            "length": 1000,
            "name": "4_membench-1M-RO-S",
            "processors": [
                {
                    "processingUnits": 1,
                    "processor": "A72"
                }
            ]
        },
        {
            "assignmentIndex": 0,
            "command": "TB_OPTS=\"--count=0 --work_done_every_sec=0.5 --work_done_str=CPU5_work_done\" ./canrdr-4K -v0 -c1 -i100",
            "length": 1000,
            "name": "5_canrdr-4K",
            "processors": [
                {
                    "processingUnits": 1,
                    "processor": "A72"
                }
            ]
        }
    ]
}